owl_finder/__init__.py
owl_finder/multiquery/__init__.py
owl_finder/multiquery/bp/__init__.py
owl_finder/multiquery/bp/find_ontology_data.py
owl_finder/multiquery/dmo/__init__.py
owl_finder/multiquery/dmo/external_synonym_loader.py
owl_finder/multiquery/dmo/model_result_merge.py
owl_finder/multiquery/dmo/ner_pallete_lookup.py
owl_finder/multiquery/dmo/span/__init__.py
owl_finder/multiquery/dmo/span/owl_span_augment.py
owl_finder/multiquery/dmo/span/owl_span_generate.py
owl_finder/multiquery/dmo/view_generator_lookup.py
owl_finder/multiquery/dmo/view_generator_nerdepth.py
owl_finder/multiquery/dmo/view_generator_nerlabel.py
owl_finder/multiquery/dmo/view_generator_nertaxo.py
owl_finder/multiquery/svc/__init__.py
owl_finder/multiquery/svc/find_ner.py
owl_finder/multiquery/svc/find_synonyms.py
owl_finder/multiquery/svc/find_types.py
owl_finder/multiquery/svc/load_synonyms.py
owl_finder/multiquery/svc/query_ner_depth.py
owl_finder/multiquery/svc/query_ner_label.py
owl_finder/multiquery/svc/query_ner_taxo.py
owl_finder/singlequery/__init__.py
owl_finder/singlequery/bp/__init__.py
owl_finder/singlequery/bp/ask_owl_api.py
owl_finder/singlequery/dmo/__init__.py
owl_finder/singlequery/dmo/owl_graph_connector.py
owl_finder/singlequery/dmo/owl_query_extract.py
owl_finder/singlequery/dmo/owl_query_normalize.py
owl_finder/singlequery/dto/__init__.py
owl_finder/singlequery/dto/query_result_type.py
owl_finder/singlequery/svc/__init__.py
owl_finder/singlequery/svc/generate_plus_spans.py
owl_finder/singlequery/svc/generate_view_spans.py
owl_finder/singlequery/svc/generate_view_synonyms.py
owl_finder/singlequery/svc/generate_view_trie.py
owl_finder/singlequery/svc/load_ontology_model.py
owl_finder/singlequery/svc/query_ontology_model.py
owl_finder-0.1.13.dist-info/METADATA
owl_finder-0.1.13.dist-info/WHEEL
owl_finder-0.1.13.dist-info/RECORD
